coolsql/__init__.py
coolsql/__version__.py
coolsql/expressions.py
coolsql/field.py
coolsql-0.1.0.dist-info/LICENSE
coolsql-0.1.0.dist-info/WHEEL
coolsql-0.1.0.dist-info/METADATA
coolsql-0.1.0.dist-info/RECORD
